setup.py
django_intellectmoney.egg-info/PKG-INFO
django_intellectmoney.egg-info/SOURCES.txt
django_intellectmoney.egg-info/dependency_links.txt
django_intellectmoney.egg-info/requires.txt
django_intellectmoney.egg-info/top_level.txt
intellectmoney/__init__.py
intellectmoney/admin.py
intellectmoney/forms.py
intellectmoney/helpers.py
intellectmoney/models.py
intellectmoney/signals.py
intellectmoney/tests.py
intellectmoney/urls.py
intellectmoney/views.py
intellectmoney/migrations/0001_initial.py
intellectmoney/migrations/0002_auto__add_field_intellectmoney_payment_id.py
intellectmoney/migrations/0003_auto__add_field_intellectmoney_order.py
intellectmoney/migrations/0004_auto.py
intellectmoney/migrations/__init__.py