Metadata-Version: 1.1
Name: django-intellectmoney
Version: 0.1.1
Summary: Приложение для работы с intellectmoney.ru
Home-page: http://www.nanobilet.ru/
Author: Andrey Beletsky
Author-email: andrey@vr2.net
License: MIT license
Platform: UNKNOWN
Classifier: Development Status :: 4 - Beta
Classifier: Environment :: Web Environment
Classifier: Framework :: Django
Classifier: Intended Audience :: Developers
Classifier: License :: OSI Approved :: MIT License
Classifier: Programming Language :: Python
Classifier: Topic :: Software Development :: Libraries :: Python Modules
Classifier: Natural Language :: Russian
